<?xml version="1.0" encoding="UTF-8"?><record_update>
    <sys_choice action="DELETE" field="u_what_needed" table="x_58872_needit_needit" version="3">
        <sys_choice_set action="DELETE">
            <element>u_what_needed</element>
            <name>x_58872_needit_needit</name>
            <sys_class_name/>
            <sys_created_by/>
            <sys_created_on/>
            <sys_id/>
            <sys_mod_count/>
            <sys_name/>
            <sys_package/>
            <sys_policy/>
            <sys_scope/>
            <sys_update_name/>
            <sys_updated_by/>
            <sys_updated_on>2020-05-05 06:33:21</sys_updated_on>
        </sys_choice_set>
    </sys_choice>
    <sys_update_version action="INSERT_OR_UPDATE">
        <action>DELETE</action>
        <application/>
        <file_path/>
        <instance_id>0dd23090db6b005452cec597059619af</instance_id>
        <instance_name>dev102659</instance_name>
        <name>sys_choice_x_58872_needit_needit_u_what_needed</name>
        <payload><![CDATA[<?xml version="1.0" encoding="UTF-8"?><record_update><sys_choice action="DELETE" field="u_what_needed" table="x_58872_needit_needit" version="3"><sys_choice_set action="DELETE"><element>u_what_needed</element><name>x_58872_needit_needit</name><sys_class_name/><sys_created_by/><sys_created_on/><sys_id/><sys_mod_count/><sys_name/><sys_package/><sys_policy/><sys_scope/><sys_update_name/><sys_updated_by/><sys_updated_on>2020-05-05 06:33:21</sys_updated_on></sys_choice_set></sys_choice></record_update>]]></payload>
        <payload_hash>-429457270</payload_hash>
        <record_name>x_58872_needit_needit.u_what_needed</record_name>
        <reverted_from/>
        <source>0bb968de2fe810108061d7a72799b6ea</source>
        <source_table>sys_update_set</source_table>
        <state>previous</state>
        <sys_created_by>admin</sys_created_by>
        <sys_created_on>2020-05-05 06:33:21</sys_created_on>
        <sys_id>f09a24922f2c10108061d7a72799b6e9</sys_id>
        <sys_mod_count>0</sys_mod_count>
        <sys_recorded_at>171e389f5090000001</sys_recorded_at>
        <sys_updated_by>admin</sys_updated_by>
        <sys_updated_on>2020-05-05 06:33:21</sys_updated_on>
        <type>Choice list</type>
        <update_guid>7c9a2492a62c10107f0a0ccdf79063e8</update_guid>
        <update_guid_history>7c9a2492a62c10107f0a0ccdf79063e8:-429457270,389a24928d2c1010fd7aaa0c7739afe5:1264701252,b49a2492382c10109cf9cca6824397e2:-1001554480,349a2492762c1010500fcde523a550df:40095198,b09a2492852c10106b3268a1343a5ddc:-964893873,309a2492022c101065319ea1f78888d9:-881906039,bc9a24923d2c1010909f503f8983cfd5:-617405790,2c9a2492bc2c1010ade8abd6c9d54ed2:172564414,ae9968529c2c1010d013ab3d3dd26a48:0,62996852982c10100222ed663dcec12c:-1459610755</update_guid_history>
    </sys_update_version>
    <sys_metadata_delete action="INSERT_OR_UPDATE">
        <sys_audit_delete/>
        <sys_class_name>sys_metadata_delete</sys_class_name>
        <sys_created_by>admin</sys_created_by>
        <sys_created_on>2020-05-05 06:33:37</sys_created_on>
        <sys_db_object display_value="" name="sys_choice_set">sys_choice_set</sys_db_object>
        <sys_id>e0aa68922f2c10108061d7a72799b637</sys_id>
        <sys_metadata>e0aa68922f2c10108061d7a72799b637</sys_metadata>
        <sys_mod_count>0</sys_mod_count>
        <sys_name>u_what_needed</sys_name>
        <sys_package display_value="NeedIt" source="x_58872_needit">6ead8e780f603200cd674f8ce1050ed1</sys_package>
        <sys_parent/>
        <sys_policy/>
        <sys_scope display_value="NeedIt">6ead8e780f603200cd674f8ce1050ed1</sys_scope>
        <sys_scope_delete display_value="">94872a8897db403e8ee69a431de2fca4</sys_scope_delete>
        <sys_update_name>sys_choice_x_58872_needit_needit_u_what_needed</sys_update_name>
        <sys_update_version display_value="sys_choice_x_58872_needit_needit_u_what_needed">f09a24922f2c10108061d7a72799b6e9</sys_update_version>
        <sys_updated_by>admin</sys_updated_by>
        <sys_updated_on>2020-05-05 06:33:37</sys_updated_on>
    </sys_metadata_delete>
</record_update>
